markovtextgen.py
markovtextgen-0.4.2.dist-info/DESCRIPTION.rst
markovtextgen-0.4.2.dist-info/METADATA
markovtextgen-0.4.2.dist-info/RECORD
markovtextgen-0.4.2.dist-info/WHEEL
markovtextgen-0.4.2.dist-info/metadata.json
markovtextgen-0.4.2.dist-info/top_level.txt
