Metadata-Version: 2.0
Name: markovtextgen
Version: 0.4.2
Summary: Simple module for text generation with a Markov model
Home-page: https://github.com/bonnieetc/markov-text
Author: Bonnie Lampard
Author-email: UNKNOWN
License: MIT
Keywords: ngram markov generator nlp
Platform: UNKNOWN
Classifier: Development Status :: 3 - Alpha
Classifier: Intended Audience :: Developers
Classifier: License :: OSI Approved :: MIT License
Classifier: Programming Language :: Python :: 3
Classifier: Programming Language :: Python :: 3.3
Classifier: Programming Language :: Python :: 3.4
Classifier: Programming Language :: Python :: 3.5
Requires-Dist: numpy
